jsonl_tools/__init__.py
jsonl_tools/convert.py
jsonl_tools/core.py
jsonl_tools/process.py
jsonl_tools-0.1.3.dist-info/LICENCE
jsonl_tools-0.1.3.dist-info/METADATA
jsonl_tools-0.1.3.dist-info/WHEEL
jsonl_tools-0.1.3.dist-info/top_level.txt
jsonl_tools-0.1.3.dist-info/RECORD
