Metadata-Version: 2.1
Name: jsonl-tools
Version: 0.1.3
Summary: A Python library for working with JSONL files
Home-page: https://github.com/vladimirkucin634/jsonl_tools
Author: vladimirkucin634
Author-email: vladimirkucin634@gmail.com
License: UNKNOWN
Platform: UNKNOWN
Classifier: Development Status :: 5 - Production/Stable
Classifier: Intended Audience :: Developers
Classifier: License :: OSI Approved :: MIT License
Classifier: Natural Language :: English
Classifier: Programming Language :: Python :: 3
Classifier: Programming Language :: Python :: 3.7
Classifier: Programming Language :: Python :: 3.8
Classifier: Programming Language :: Python :: 3.9
Classifier: Programming Language :: Python :: 3.10
Classifier: Programming Language :: Python :: 3.11
Requires-Python: >=3.7
